selectcoma_de_toolkit/__init__.py
selectcoma_de_toolkit/main.py
selectcoma_de_toolkit/vm.py
selectcoma_de_toolkit-0.1.0.dist-info/METADATA
selectcoma_de_toolkit-0.1.0.dist-info/WHEEL
selectcoma_de_toolkit-0.1.0.dist-info/entry_points.txt
selectcoma_de_toolkit-0.1.0.dist-info/RECORD
